{"statusCode": 200, "body": "{\"success\": false, \"url\": \"https://example.com\", \"result\": {\"success\": false, \"url\": \"https://example.com\", \"error\": \"All proxy modes failed for https://example.com\", \"crawl_time\": 14.01, \"stats\": {\"total_requests\": 5, \"total_successes\": 0, \"total_failures\": 2, \"success_rate\": 0.0, \"mode_breakdown\": {\"standard\": {\"requests\": 2, \"successes\": 0, \"failures\": 0, \"success_rate\": 0.0, \"credits_used\": 10}, \"premium\": {\"requests\": 2, \"successes\": 0, \"failures\": 1, \"success_rate\": 0.0, \"credits_used\": 50}, \"stealth\": {\"requests\": 1, \"successes\": 0, \"failures\": 1, \"success_rate\": 0.0, \"credits_used\": 75}}, \"site_requirements\": {}}}, \"usage_stats\": {\"scrapingbee_stats\": {\"total_requests\": 5, \"total_successes\": 0, \"total_failures\": 2, \"success_rate\": 0.0, \"mode_breakdown\": {\"standard\": {\"requests\": 2, \"successes\": 0, \"failures\": 0, \"success_rate\": 0.0, \"credits_used\": 10}, \"premium\": {\"requests\": 2, \"successes\": 0, \"failures\": 1, \"success_rate\": 0.0, \"credits_used\": 50}, \"stealth\": {\"requests\": 1, \"successes\": 0, \"failures\": 1, \"success_rate\": 0.0, \"credits_used\": 75}}, \"site_requirements\": {}}, \"cost_estimate\": {\"total_cost\": 0.135, \"mode_costs\": {\"standard\": 0.01, \"premium\": 0.05, \"stealth\": 0.075}, \"credits_used\": 135}, \"site_requirements\": {}}, \"progressive_strategy_used\": true, \"cost_analysis\": {\"total_cost\": 0.135, \"credits_used\": 135, \"mode_breakdown\": {\"standard\": 0.01, \"premium\": 0.05, \"stealth\": 0.075}}}"}